dj_enum/__init__.py
dj_enum/exceptions.py
dj_enum/fields.py
dj_enum/utils.py
dj_enum/tests/__init__.py
dj_enum/tests/models.py
dj_enum/tests/test_module.py
dj_enum/tests/test_settings.py
dj_enum-0.0.3.dist-info/LICENSE
dj_enum-0.0.3.dist-info/METADATA
dj_enum-0.0.3.dist-info/WHEEL
dj_enum-0.0.3.dist-info/top_level.txt
dj_enum-0.0.3.dist-info/RECORD
